gardner/__about__.py
gardner/__init__.py
gardner-0.0.1.dist-info/METADATA
gardner-0.0.1.dist-info/WHEEL
gardner-0.0.1.dist-info/licenses/LICENSE.txt
gardner-0.0.1.dist-info/RECORD
