Metadata-Version: 2.1
Name: gardner
Version: 0.0.1
Summary: gardner, to keep your forest and gardens neat, tree by tree
Project-URL: Documentation, https://github.com/unknown/gardner#readme
Project-URL: Issues, https://github.com/unknown/gardner/issues
Project-URL: Source, https://github.com/unknown/gardner
Author-email: Aarmn the limitless <aarmn80@gmail.com>
License-Expression: MIT
License-File: LICENSE.txt
Classifier: Development Status :: 4 - Beta
Classifier: Programming Language :: Python
Classifier: Programming Language :: Python :: 3.7
Classifier: Programming Language :: Python :: 3.8
Classifier: Programming Language :: Python :: 3.9
Classifier: Programming Language :: Python :: 3.10
Classifier: Programming Language :: Python :: 3.11
Classifier: Programming Language :: Python :: Implementation :: CPython
Classifier: Programming Language :: Python :: Implementation :: PyPy
Requires-Python: >=3.7
